simpleapp/__init__.py
simpleapp/argparse.py
simpleapp/changes.py
simpleapp/pipeline.py
simpleapp/project.py
simpleapp/toml.py
simpleapp/__pyinstaller/__init__.py
simpleapp/examples/__init__.py
simpleapp/examples/nothing.py
simpleapp/examples/runregchanges.py
simpleapp/examples/uniraw.py
simpleapp-0.1.1.dist-info/LICENSE.md
simpleapp-0.1.1.dist-info/METADATA
simpleapp-0.1.1.dist-info/WHEEL
simpleapp-0.1.1.dist-info/entry_points.txt
simpleapp-0.1.1.dist-info/top_level.txt
simpleapp-0.1.1.dist-info/RECORD
