Metadata-Version: 2.2
Name: simpleapp
Version: 0.1.1
Summary: Simple app development around Gooey and argparse
Author-email: Martin Hosken <fonts@sil.org>
License: MIT License
Project-URL: Home-Page, https://github.com/silnrsi/python-simpleapp
Classifier: Environment :: Console
Classifier: Programming Language :: Python :: 3.8
Classifier: Intended Audience :: Developers
Classifier: License :: OSI Approved :: MIT License
Classifier: Topic :: Software Development :: Libraries :: Application Frameworks
Requires-Python: >=3.8
License-File: LICENSE.md
Requires-Dist: gooey==1.0.8.1
Provides-Extra: git
